{
  "map": {
    "interaction": "dynamic",
    "viewSettings": {
      "projection": 3978
    },
    "basemapOptions": {
      "basemapId": "transport",
      "shaded": false,
      "labeled": true
    }
  },
  "theme": "geo.ca",
  "components": ["north-arrow", "overview-map"],
  "corePackages": [],
  "appBar": {
    "tabs": {
      "core": ["about-panel"]
    }
  },
  "corePackagesConfig": [
    {
      "about-panel": {
        "isOpen": true,
        "mdContent": [
          "# Atlas of Canada\n\n![Atlas Banner](./img/atlas_banner.png)",
          "## Discover Canada through geography\n\nThe Atlas of Canada provides interactive and static maps of Canada, from past to present.",
          "## Key Features\n\n- **Interactive Maps** - Dynamic maps with multiple thematic layers\n- **Historical Archive** - Digitized atlas editions from 1906 onwards\n- **Educational Resources** - Teaching materials and data for geography curriculum",
          "## Learn More\n\nExplore the full Atlas of Canada:\n\n[Visit the Atlas of Canada →](https://natural-resources.canada.ca/maps-tools-publications/maps/atlas-canada)"
        ]
      }
    }
  ]
}
